yesterdaypy/__init__.py
yesterdaypy/product.py
yesterdaypy/utils.py
yesterdaypy/version.py
yesterdaypy/yesterdaypy.py
yesterdaypy-1.1.1.dist-info/licenses/LICENSE
yesterdaypy-1.1.1.dist-info/METADATA
yesterdaypy-1.1.1.dist-info/WHEEL
yesterdaypy-1.1.1.dist-info/entry_points.txt
yesterdaypy-1.1.1.dist-info/top_level.txt
yesterdaypy-1.1.1.dist-info/RECORD
