Metadata-Version: 2.4
Name: yesterdaypy
Version: 1.1.1
Summary: A Python software to backup Linode configuration to a local folder or Linode Object Storage
Author: Leonardo Souza
License: MIT License
Project-URL: Homepage, https://github.com/leonardobdes/yesterdaypy
Project-URL: Documentation, https://github.com/leonardobdes/yesterdaypy
Project-URL: Repository, https://github.com/leonardobdes/yesterdaypy.git
Project-URL: Issues, https://github.com/leonardobdes/yesterdaypy/issues
Keywords: linode,backup
Requires-Python: >=3.9
License-File: LICENSE
Requires-Dist: linode_api4
Dynamic: license-file
